zerodha_brokerage_calculator/__init__.py
zerodha_brokerage_calculator/calculator.py
zerodha_brokerage_calculator-0.2.0.dist-info/LICENSE
zerodha_brokerage_calculator-0.2.0.dist-info/METADATA
zerodha_brokerage_calculator-0.2.0.dist-info/WHEEL
zerodha_brokerage_calculator-0.2.0.dist-info/top_level.txt
zerodha_brokerage_calculator-0.2.0.dist-info/RECORD
