Metadata-Version: 2.1
Name: zerodha_brokerage_calculator
Version: 0.2.0
Summary: A Python package to calculate Zerodha brokerage charges for various trading segments
Home-page: https://github.com/hemangjoshi37a/Zerodha-Brokerage-Calculator
Author: Hemang Joshi
Author-email: hemangjoshi37a@gmail.com
Classifier: Programming Language :: Python :: 3
Classifier: Intended Audience :: Financial and Insurance Industry
Classifier: License :: OSI Approved :: MIT License
Requires-Python: >=3.6
License-File: LICENSE
